termdraw/__init__.py
termdraw/cli.py
termdraw/csv.py
termdraw/graph.py
termdraw/interpolate.py
termdraw/termdraw.py
termdraw/terminal.py
termdraw-0.1.data/scripts/termdraw
termdraw-0.1.dist-info/DESCRIPTION.rst
termdraw-0.1.dist-info/METADATA
termdraw-0.1.dist-info/RECORD
termdraw-0.1.dist-info/WHEEL
termdraw-0.1.dist-info/metadata.json
termdraw-0.1.dist-info/top_level.txt
