Metadata-Version: 2.0
Name: termdraw
Version: 0.1
Summary: Utility library for textual data visualization
Home-page: https://github.com/bacondropped/termdraw
Author: Ilya Terentyev
Author-email: bacondropped@gmail.com
License: MIT
Keywords: data graph ascii visualization
Platform: UNKNOWN
Classifier: Environment :: Console
Classifier: Intended Audience :: Developers
Classifier: Intended Audience :: Science/Research
Classifier: License :: Freely Distributable
Classifier: Programming Language :: Python :: 3 :: Only
Classifier: Topic :: Scientific/Engineering :: Visualization
Classifier: Topic :: Utilities
